[ { "title": "[Git] 폴더명과 파일명의 대소문자 구분하기", "description": "Git에서 폴더명과 파일명의 대소문자를 구분하도록 설정하는 방법에 대해서 알아보도록 하겠습니다.","url": "https://dev-yakuza.posstree.com/ko/git/case-sensitive/","date": "2023-06-26T15:59:44+09:00", "category": "git" },{ "title": "[Git] 마지막 커밋 메시지의 작성자 수정", "description": "Git에서 amend과 author 옵션을 사용하여 마지막 커밋 메시지의 작성자를 수정하는 방법에 대해서 알아봅시다.","url": "https://dev-yakuza.posstree.com/ko/git/amend-author/","date": "2023-04-08T21:55:59+09:00", "category": "git" },{ "title": "[Git] 마지막 커밋 메시지 수정", "description": "Git에서 amend 옵션을 사용하여 마지막 커밋 메시지를 수정하는 방법에 대해서 알아봅시다.","url": "https://dev-yakuza.posstree.com/ko/git/amend/","date": "2023-04-07T11:23:31+09:00", "category": "git" },{ "title": "git stash", "description": "Git에서 git stash를 사용하여, 현재 작업중인 내용을 임시로 저장하는 방법에 대해서 알아봅시다.","url": "https://dev-yakuza.posstree.com/ko/git/stash/","date": "2021-07-24T10:38:21+09:00", "category": "git" },{ "title": "git branch와 git merge", "description": "Git을 사용하여 버전을 관리할 때 브랜치를 만들고 병합(Merge)하는 방법에 대해서 알아봅시다.","url": "https://dev-yakuza.posstree.com/ko/git/branch-merge/","date": "2022-07-17T20:22:11+09:00", "category": "git" },{ "title": "[Git] 기본 브랜치를 master에서 main으로 설정하기", "description": "Git을 사용할 때, 기본 브랜치를 master에서 main으로 변경하는 방법에 대해서 알아봅시다.","url": "https://dev-yakuza.posstree.com/ko/git/default-branch/","date": "2021-07-16T22:12:13+09:00", "category": "git" },{ "title": "Git FTP를 사용하여 파일 업로드하기", "description": "FTP를 통해 파일을 업로드하기 위해 Git FTP를 사용하는 방법에 대해서 알아봅시다.","url": "https://dev-yakuza.posstree.com/ko/git/git-ftp/","date": "2023-04-08T21:55:59+09:00", "category": "git" },{ "title": "Git squash로 여러 커밋을 하나로 만들기", "description": "Git squash를 사용하여 여러 커밋을 하나의 커밋으로 만드는 방법에 대해서 알아봅니다.","url": "https://dev-yakuza.posstree.com/ko/git/git-squash/","date": "2020-12-16T11:10:57+09:00", "category": "git" },{ "title": "Fork 저장소 동기화하기", "description": "Fork한 저장소(Repository)와 원본 저장소(Repository)를 동기화(Sync)하는 방법에 대해서 알아봅시다.","url": "https://dev-yakuza.posstree.com/ko/git/sync-fork-repository/","date": "2020-12-16T11:10:57+09:00", "category": "git" },{ "title": "버전(변경이력) 생성", "description": "git의 저장소(Repository)로 버전 관리를 하기 위해 버전(변경 이력)을 생성하는 방법에 대해서 알아봅니다.","url": "https://dev-yakuza.posstree.com/ko/git/create-stage/","date": "2023-03-18T10:37:27+09:00", "category": "git" },{ "title": "저장소(Repository) 생성", "description": "git를 사용하기 위해 git의 저장소(Repository)를 생성합니다. git의 저장소(Repository)는 소스 코드의 버전을 관리하기 위한 저장 장소입니다.","url": "https://dev-yakuza.posstree.com/ko/git/create-repository/","date": "2023-03-18T10:37:27+09:00", "category": "git" },{ "title": "git 설치", "description": "소스 코드의 버전 관리를 위해 git을 사용하려고 합니다. git을 사용하기 위해 git을 설치합니다.","url": "https://dev-yakuza.posstree.com/ko/git/installation/","date": "2023-03-18T10:37:27+09:00", "category": "git" }]