[{ "title": "ジャンゴ(django)のルーティング(Routing)", "description": "ジャンゴ(django)のURL管理機能を使ってウェブサービスのルーティング(Routing)を管理してみましょう。","url": "https://dev-yakuza.github.io/django/routing/","date": "2019-05-20T13:25:27+09:00", "page": "1" },{ "title": "ジャンゴ(django)の管理者ページ", "description": "ジャンゴ(django)が基本的提供してる管理者ページを使う方法について説明します。","url": "https://dev-yakuza.github.io/django/admin/","date": "2019-05-19T22:21:31+09:00", "page": "1" },{ "title": "ジャンゴ(django)のモデル(models)の使い方", "description": "ジャンゴ(django)のプロジェクトにアプリケーションを生成して新しアプリケーションに必要なデーターを保存するモデル(models)を生成して使う方法について説明します。","url": "https://dev-yakuza.github.io/django/models/","date": "2019-05-16T14:12:54+09:00", "page": "1" },{ "title": "ジャンゴ(django)のプロジェクト開始", "description": "ジャンゴ(django)のコマンドでジャンゴ(django)のプロジェクトを生成して開始してみましょう。 また、設定、DB(mysql)連動をして実際ジャンゴ(django)でプロジェクトを開発できるようにしてみましょう","url": "https://dev-yakuza.github.io/django/start/","date": "2019-05-15T10:47:47+09:00", "page": "1" },{ "title": "ジャンゴ(django)インストール", "description": "ジャンゴ(django)で開発するためジャンゴ(django)をインストールして設定する方法について説明します。","url": "https://dev-yakuza.github.io/django/installation/","date": "2019-05-07T21:23:34+09:00", "page": "1" }]